csxhair/__init__.py
csxhair-1.0.1.dist-info/LICENSE
csxhair-1.0.1.dist-info/METADATA
csxhair-1.0.1.dist-info/WHEEL
csxhair-1.0.1.dist-info/top_level.txt
csxhair-1.0.1.dist-info/RECORD
