Metadata-Version: 2.1
Name: csxhair
Version: 1.0.1
Summary: Decode, edit and encode CS:GO/CS2 crosshairs easily.
Author: SyberiaK
License: MIT License
Project-URL: Homepage, https://github.com/SyberiaK/csxhair
Project-URL: Issues, https://github.com/SyberiaK/csxhair/issues
Classifier: Development Status :: 6 - Mature
Classifier: Intended Audience :: Developers
Classifier: License :: OSI Approved :: MIT License
Classifier: Operating System :: OS Independent
Classifier: Programming Language :: Python :: 3.8
Classifier: Programming Language :: Python :: 3.9
Classifier: Programming Language :: Python :: 3.10
Classifier: Programming Language :: Python :: 3.11
Classifier: Programming Language :: Python :: 3.12
Classifier: Topic :: Utilities
Classifier: Typing :: Typed
Requires-Python: >=3.8
License-File: LICENSE
Requires-Dist: attrs >=23.1.0
